{
  "_class": "group",
  "booleanOperation": 0,
  "clippingMaskMode": 0,
  "do_objectID": "1372E686-E2F0-4571-91C1-0953B0AE5BAB",
  "exportOptions": {
    "_class": "exportOptions",
    "exportFormats": [
    ],
    "includedLayerIds": [
    ],
    "layerOptions": 0,
    "shouldTrim": false
  },
  "frame": {
    "_class": "rect",
    "constrainProportions": false,
    "height": 4.77064220183486,
    "width": 36.3917775090689,
    "x": 38.59733978234581,
    "y": 0.09174311926605504
  },
  "groupLayout": {
    "_class": "MSImmutableFreeformGroupLayout"
  },
  "hasClickThrough": false,
  "hasClippingMask": false,
  "isFixedToViewport": false,
  "isFlippedHorizontal": false,
  "isFlippedVertical": false,
  "isLocked": false,
  "isVisible": true,
  "layerListExpandedType": 0,
  "layers": [
    {
      "class": "shapePath",
      "id": "D513E5CD-8E86-4B00-9A16-176E45D21F1A"
    },
    {
      "class": "shapePath",
      "id": "893EAE54-54E6-4A50-96E6-4D7BDBBE719D"
    },
    {
      "class": "shapePath",
      "id": "B6B4B4FC-D4A0-4350-BED9-03F52C6A91E5"
    },
    {
      "class": "shapeGroup",
      "id": "8FD8B679-8451-4224-97D4-5BDC19F1FF6F"
    },
    {
      "class": "shapeGroup",
      "id": "7A27224A-7080-43F3-82E3-737AF8B0E682"
    },
    {
      "class": "shapeGroup",
      "id": "7E2ECD81-8EB0-4C8C-B8D4-4EB23C963D53"
    },
    {
      "class": "shapePath",
      "id": "595366D6-AAE1-444F-9BE5-0746CEE2A0FB"
    },
    {
      "class": "shapeGroup",
      "id": "700D0A6D-47BD-4D81-8D23-180A9ED8D4E0"
    },
    {
      "class": "shapeGroup",
      "id": "28787826-670D-4C54-A080-94E13D98F093"
    },
    {
      "class": "shapePath",
      "id": "5419034C-7EBB-4E66-BAC2-F8771FB0E3A3"
    },
    {
      "class": "shapeGroup",
      "id": "54084FAE-7BA7-4D46-99D2-CD679BB50E3C"
    },
    {
      "class": "shapePath",
      "id": "AB3B060A-A7B1-4B29-A489-753A793A5369"
    },
    {
      "class": "shapeGroup",
      "id": "35C4997F-D300-42E8-87A2-F4639D4D37C2"
    },
    {
      "class": "shapeGroup",
      "id": "D3B77B3F-5053-4B87-B5E1-87AD9FDD0C0A"
    },
    {
      "class": "shapePath",
      "id": "4F12B6B0-C246-4D40-A290-14DE86010386"
    },
    {
      "class": "shapeGroup",
      "id": "403545AE-47A1-40AE-A2C7-94F2FC4F3A92"
    }
  ],
  "maintainScrollPosition": false,
  "name": "Group",
  "nameIsFixed": false,
  "resizingConstraint": 63,
  "resizingType": 0,
  "rotation": 0,
  "shouldBreakMaskChain": false,
  "style": {
    "_class": "style",
    "blur": {
      "_class": "blur",
      "center": "{0.5, 0.5}",
      "isEnabled": false,
      "motionAngle": 0,
      "radius": 0.9174311926605504,
      "saturation": 1,
      "type": 0
    },
    "borderOptions": {
      "_class": "borderOptions",
      "dashPattern": [
      ],
      "isEnabled": true,
      "lineCapStyle": 0,
      "lineJoinStyle": 0
    },
    "borders": [
    ],
    "colorControls": {
      "_class": "colorControls",
      "brightness": 0,
      "contrast": 1,
      "hue": 0,
      "isEnabled": false,
      "saturation": 1
    },
    "contextSettings": {
      "_class": "graphicsContextSettings",
      "blendMode": 0,
      "opacity": 1
    },
    "do_objectID": "9504BE80-E26B-4F00-B326-7FD174159F98",
    "endMarkerType": 0,
    "fills": [
      {
        "_class": "fill",
        "color": {
          "_class": "color",
          "alpha": 1,
          "blue": 0,
          "green": 0,
          "red": 0
        },
        "contextSettings": {
          "_class": "graphicsContextSettings",
          "blendMode": 0,
          "opacity": 1
        },
        "fillType": 0,
        "gradient": {
          "_class": "gradient",
          "elipseLength": 0,
          "from": "{0.5, 0}",
          "gradientType": 0,
          "stops": [
            {
              "_class": "gradientStop",
              "color": {
                "_class": "color",
                "alpha": 1,
                "blue": 1,
                "green": 1,
                "red": 1
              },
              "position": 0
            },
            {
              "_class": "gradientStop",
              "color": {
                "_class": "color",
                "alpha": 1,
                "blue": 0,
                "green": 0,
                "red": 0
              },
              "position": 1
            }
          ],
          "to": "{0.5, 1}"
        },
        "isEnabled": true,
        "noiseIndex": 0,
        "noiseIntensity": 0,
        "patternFillType": 1,
        "patternTileScale": 1
      }
    ],
    "innerShadows": [
    ],
    "miterLimit": 10,
    "shadows": [
    ],
    "startMarkerType": 0,
    "windingRule": 1
  }
}