{
  "_class": "artboard",
  "backgroundColor": {
    "_class": "color",
    "alpha": 1,
    "blue": 1,
    "green": 1,
    "red": 1
  },
  "booleanOperation": -1,
  "clippingMaskMode": 0,
  "do_objectID": "4BAD8DFD-07A1-48CF-93C7-4DF44FDBD3A8",
  "exportOptions": {
    "_class": "exportOptions",
    "exportFormats": [
      {
        "_class": "exportFormat",
        "absoluteSize": 0,
        "fileFormat": "jpg",
        "name": "",
        "namingScheme": 0,
        "scale": 1,
        "visibleScaleType": 0
      }
    ],
    "includedLayerIds": [
    ],
    "layerOptions": 0,
    "shouldTrim": false
  },
  "frame": {
    "_class": "rect",
    "constrainProportions": false,
    "height": 2638,
    "width": 1160,
    "x": -580,
    "y": -1320
  },
  "groupLayout": {
    "_class": "MSImmutableFreeformGroupLayout"
  },
  "hasBackgroundColor": true,
  "hasClickThrough": true,
  "hasClippingMask": false,
  "horizontalRulerData": {
    "_class": "rulerData",
    "base": 0,
    "guides": [
    ]
  },
  "includeBackgroundColorInExport": true,
  "includeInCloudUpload": true,
  "isFixedToViewport": false,
  "isFlippedHorizontal": false,
  "isFlippedVertical": false,
  "isFlowHome": false,
  "isLocked": false,
  "isVisible": true,
  "layerListExpandedType": 2,
  "layers": [
    {
      "class": "group",
      "id": "CDFE5552-9EF7-41BD-B639-2D4092CBDB38"
    },
    {
      "class": "rectangle",
      "id": "4A87BF45-7D0C-4C84-A7CD-A919614DA664"
    },
    {
      "class": "rectangle",
      "id": "8EAC6937-7E2E-473A-8414-D383B7600E6B"
    },
    {
      "class": "rectangle",
      "id": "1681A454-4148-4408-B7CD-A2F885B65958"
    },
    {
      "class": "rectangle",
      "id": "9F427A7C-08D7-4242-8B6F-E9853781071B"
    },
    {
      "class": "rectangle",
      "id": "8A1BBDCC-28C1-477A-9BFD-A398A07AF9A3"
    },
    {
      "class": "rectangle",
      "id": "5458F2DE-FE84-4068-A877-36BB04B30640"
    },
    {
      "class": "rectangle",
      "id": "D1A52263-2A1B-4CF5-B58F-67C7AB1222A9"
    },
    {
      "class": "rectangle",
      "id": "32DC6B38-7D11-4640-9AF0-33FBB5543EEF"
    },
    {
      "class": "rectangle",
      "id": "6844D859-C54D-45BB-8E50-5252F62A94BB"
    },
    {
      "class": "rectangle",
      "id": "9AFBC96F-7A54-4E8B-BECC-FB32CF3644EB"
    },
    {
      "class": "rectangle",
      "id": "11A4D8DD-E302-4D74-8CBC-A5487F545B33"
    },
    {
      "class": "text",
      "id": "CCFAD64B-B233-459C-8497-CD3D6AF63AD7"
    },
    {
      "class": "text",
      "id": "05C4CC47-5141-4D2D-9400-5FAED645795C"
    },
    {
      "class": "text",
      "id": "C29946FC-0EF0-4477-A1A3-0B1BB3F454A2"
    },
    {
      "class": "text",
      "id": "E9F2905C-02AE-46F7-B715-2BB7AC7E3108"
    },
    {
      "class": "text",
      "id": "6C7BD722-A65A-498F-BD52-576B18A2D9D7"
    },
    {
      "class": "text",
      "id": "40EBDF92-E107-444D-ADF9-2FBB66F5958C"
    },
    {
      "class": "text",
      "id": "E5D5108C-44DE-4D3B-AAD2-1DE132CA6963"
    },
    {
      "class": "text",
      "id": "979ACC6B-68C0-4FB2-8E1E-41E94895F1A2"
    },
    {
      "class": "text",
      "id": "14A44EFD-CECA-4741-BB3E-61F4818D0F9B"
    },
    {
      "class": "text",
      "id": "74BE1580-9F1E-408D-9E9C-BE912963547D"
    },
    {
      "class": "text",
      "id": "2B003942-E98F-4B30-8536-AD30292D8CB2"
    },
    {
      "class": "text",
      "id": "4F548150-28AD-4D7C-94A2-858FB281DF5C"
    },
    {
      "class": "text",
      "id": "E4FBD4C1-AB4B-4417-AA80-E73586DDE67F"
    },
    {
      "class": "text",
      "id": "D909D132-48D3-4266-8BDE-D8E5A0582CEB"
    },
    {
      "class": "text",
      "id": "C3E4AFB0-7A25-4F1F-A3BF-B5C41E6B7A4B"
    },
    {
      "class": "text",
      "id": "72BAE6B2-AB55-49DD-ABEF-337F077720A4"
    },
    {
      "class": "text",
      "id": "B4C866B5-7FD1-4123-856B-B67899C9BA85"
    },
    {
      "class": "text",
      "id": "EC14384F-C312-4D51-ACA9-3A576E35988B"
    },
    {
      "class": "text",
      "id": "7740F974-4C57-4CA8-A7BE-B0D4A1CD49F6"
    },
    {
      "class": "text",
      "id": "4ED499E9-AD74-435E-B313-B2DA55AB2672"
    },
    {
      "class": "text",
      "id": "4807E80B-4653-4AFC-9848-3C624E9A776C"
    },
    {
      "class": "text",
      "id": "1943F0C0-B387-4156-A897-3CF6187F6F9E"
    },
    {
      "class": "text",
      "id": "E24781A1-0DD0-4946-8888-CB16EF52C1BB"
    },
    {
      "class": "text",
      "id": "E4A62689-A7AC-4FB1-A41B-32A22960ADB9"
    },
    {
      "class": "text",
      "id": "8249C0A4-A4AF-47B0-948B-920025CB4DFE"
    },
    {
      "class": "text",
      "id": "A6BFE35C-DA4F-4A96-A6EF-6CDA6C25E938"
    },
    {
      "class": "text",
      "id": "FDFB98AA-BD3F-4A9E-8A27-0D03D451ABB3"
    },
    {
      "class": "shapePath",
      "id": "D42ED66D-5A94-40A1-8979-F0939043C4A1"
    },
    {
      "class": "shapePath",
      "id": "47500BC1-0A01-4759-A184-67663A3EB608"
    }
  ],
  "maintainScrollPosition": false,
  "name": "Spacings",
  "nameIsFixed": true,
  "presetDictionary": {
  },
  "resizesContent": false,
  "resizingConstraint": 63,
  "resizingType": 0,
  "rotation": 0,
  "shouldBreakMaskChain": true,
  "style": {
    "_class": "style",
    "blur": {
      "_class": "blur",
      "center": "{0.5, 0.5}",
      "isEnabled": false,
      "motionAngle": 0,
      "radius": 10,
      "saturation": 1,
      "type": 0
    },
    "borderOptions": {
      "_class": "borderOptions",
      "dashPattern": [
      ],
      "isEnabled": true,
      "lineCapStyle": 0,
      "lineJoinStyle": 0
    },
    "borders": [
    ],
    "colorControls": {
      "_class": "colorControls",
      "brightness": 0,
      "contrast": 1,
      "hue": 0,
      "isEnabled": false,
      "saturation": 1
    },
    "contextSettings": {
      "_class": "graphicsContextSettings",
      "blendMode": 0,
      "opacity": 1
    },
    "do_objectID": "2D006722-7496-410C-A929-51249192D6B0",
    "endMarkerType": 0,
    "fills": [
    ],
    "innerShadows": [
    ],
    "miterLimit": 10,
    "shadows": [
    ],
    "startMarkerType": 0,
    "windingRule": 1
  },
  "verticalRulerData": {
    "_class": "rulerData",
    "base": 0,
    "guides": [
    ]
  }
}